yuriko/__init__.py
yuriko/main.py
yuriko/manager.py
yuriko/password.py
yuriko/settings.py
yuriko/tests.py
yuriko-0.0.4.dist-info/LICENSE
yuriko-0.0.4.dist-info/METADATA
yuriko-0.0.4.dist-info/WHEEL
yuriko-0.0.4.dist-info/entry_points.txt
yuriko-0.0.4.dist-info/top_level.txt
yuriko-0.0.4.dist-info/RECORD
