Metadata-Version: 2.1
Name: yuriko
Version: 0.0.4
Summary: Encrypted notes
Home-page: https://github.com/nanvel/yuriko
Author: Oleksandr Polieno
Author-email: polyenoom@gmail.com
License: The MIT License
Keywords: encrypted,notes
Platform: OS Independent
License-File: LICENSE
Requires-Dist: PyCryptodome
